{
    "accentColor": "#0089BF",
    "logoUrl": "https://github.com/Teknikio/pxt-teknikio",
    "logo": "docs/static/logo.png",
    "organization": "Teknikio",
    "organizationUrl": "https://www.teknikio.com/",
    "organizationLogo": "https://cdn.shopify.com/s/files/1/1837/7355/files/logo_larger_600x.png?v=1572991143",
    "organizationWideLogo": "https://cdn.shopify.com/s/files/1/1837/7355/files/logo_larger_600x.png?v=1572991143",
    "homeUrl": "https://www.teknikio.com/pages/bluebird",
    "embedUrl": "https://www.teknikio.com/pages/bluebird",
    "privacyUrl": "https://www.teknikio.com/pages/privacy-policy",
    "termsOfUseUrl": "https://www.teknikio.com/pages/terms-and-conditions",
    "githubUrl": "https://github.com/Teknikio/pxt-teknikio",
    "boardName": "board",
    "driveDisplayName": "DRIVE",
    "uploadMessage": "Download",
    "docMenu": [
        {
            "name": "About",
            "path": "https://teknikio.github.io/docs/about"
        },
        {
            "name": "Docs",
            "path": "https://teknikio.github.io/docs/about"
        },
        {
            "name": "Reference",
            "path": "https://teknikio.github.io/docs/reference"
        },
        {
            "name": "FAQ",
            "path": "https://teknikio.github.io/docs/faq"
        }
    ],
    "hasReferenceDocs": true,
    "coloredToolbox": false,
    "monacoToolbox": true,
    "invertedMenu": true,
    "invertedToolbox": true,
    "invertedMonaco": true,
    "selectLanguage": true,
    "availableLocales": [
        "en",
        "de",
        "ja",
        "es-ES",
        "fi",
        "fr",
        "hu",
        "is",
        "it",
        "ko",
        "nl",
        "no",
        "pt-BR",
        "pt-PT",
        "ru",
        "si-LK",
        "sk",
        "sv-SE",
        "tr",
        "uk",
        "zh-CN",
        "zh-TW"
    ],
    "showHomeScreen": true,
    "homeScreenHero": "docs/static/hero.png",
    "blocklyOptions": {
        "grid": {
            "spacing": 20,
            "length": 2,
            "colour": "#fdf4e8",
            "snap": true
        }
    },
    "blocklyColors": {
        "insertionMarker": "#FFFFFF",
        "insertionMarkerOpacity": 0.5
    },
    "blockColors": {
        "pins": "#185C87",
        "mixer": "#185C87",
        "variables": "#E6B901",
        "math": "#E6B901",
        "loops": "#7ED321",
        "logic": "#7ED321",
        "text": "#ffab19",
        "advanced": "#F04D3A",
        "functions": "#005a9e",
        "arrays": "#8A1C7C"
    },
    "allowPackageExtensions": true,
    "alwaysGithubItem": true,
    "monacoColors": {
        "editor.background": "#ecf0f1"
    },
    "socialOptions": {
        "orgTwitterHandle": "teknikio"
    },
    "simAnimationEnter": "roll in",
    "simAnimationExit": "roll out",
    "allowParentController": false,
    "hideMenuBar": false,
    "hideEditorToolbar": false,
    "hideCookieNotice": true,
    "debugger": true,
    "highContrast": true,
    "greenScreen": true,
    "enableTrace": true,
    "print": true,
    "hasAudio": true,
    "extendEditor": true,
    "extendFieldEditors": true,
    "disableBlockIcons": true,
    "scriptManager": true,
    "baseTheme": "dark",
    "qrCode": true,
    "python": true,
    "pythonToolbox": true,
    "TOC": [
        {
            "name": "About",
            "path": "/about",
            "subitems": []
        },
        {
            "name": "Control Center",
            "path": "/controlcenter",
            "subitems": []
        },
        {
            "name": "Examples",
            "path": "/demos",
            "subitems": [
                {
                    "name": "Siren",
                    "path": "/demos/siren",
                    "subitems": []
                },
                {
                    "name": "Magic Wand",
                    "path": "/demos/magicwand",
                    "subitems": []
                },
                {
                    "name": "Nightlight",
                    "path": "/demos/nightlight",
                    "subitems": []
                },
                {
                    "name": "PushUp Counter",
                    "path": "/demos/pushupcounter",
                    "subitems": []
                },
                {
                    "name": "Smart Timer Cube",
                    "path": "/demos/timer",
                    "subitems": []
                },
                {
                    "name": "Sunset Mountain",
                    "path": "/demos/nightlight",
                    "subitems": []
                },
                {
                    "name": "Conductor's Baton",
                    "path": "/demos/baton",
                    "subitems": []
                },
                {
                    "name": "Domino Effect",
                    "path": "/demos/domino_effect",
                    "subitems": []
                },
                {
                    "name": "Simon Says",
                    "path": "/demos/simonsays",
                    "subitems": []
                }
            ]
        },
        {
            "name": "Hardware",
            "path": "/hardware",
            "subitems": []
        },
        {
            "name": "GitHub",
            "path": "/github",
            "subitems": []
        },
        {
            "name": "Hardware Blocks",
            "path": "/reference",
            "subitems": [
                {
                    "name": "Basic",
                    "path": "/reference/basic",
                    "subitems": [
                        {
                            "name": "show number",
                            "path": "/reference/basic/show-number",
                            "subitems": []
                        },
                        {
                            "name": "show icon",
                            "path": "/reference/basic/show-icon",
                            "subitems": []
                        },
                        {
                            "name": "show leds",
                            "path": "/reference/basic/show-leds",
                            "subitems": []
                        },
                        {
                            "name": "show string",
                            "path": "/reference/basic/show-string",
                            "subitems": []
                        },
                        {
                            "name": "clear screen",
                            "path": "/reference/basic/clear-screen",
                            "subitems": []
                        },
                        {
                            "name": "forever",
                            "path": "/reference/basic/forever",
                            "subitems": []
                        },
                        {
                            "name": "pause",
                            "path": "/reference/basic/pause",
                            "subitems": []
                        },
                        {
                            "name": "show arrow",
                            "path": "/reference/basic/show-arrow",
                            "subitems": []
                        },
                        {
                            "name": "show animation",
                            "path": "/reference/basic/show-animation",
                            "subitems": []
                        }
                    ]
                },
                {
                    "name": "Sensors",
                    "path": "/reference/sensors",
                    "subitems": [
                        {
                            "name": "on gesture",
                            "path": "/reference/input/on-gesture",
                            "subitems": []
                        },
                        {
                            "name": "on pin pressed",
                            "path": "/reference/input/on-pin-pressed",
                            "subitems": []
                        },
                        {
                            "name": "pin is pressed",
                            "path": "/reference/input/pin-is-pressed",
                            "subitems": []
                        },
                        {
                            "name": "temperature",
                            "path": "/reference/input/temperature",
                            "subitems": []
                        },
                        {
                            "name": "acceleration",
                            "path": "/reference/input/acceleration",
                            "subitems": []
                        },
                        {
                            "name": "light level",
                            "path": "/reference/input/light-level",
                            "subitems": []
                        },
                        {
                            "name": "rotation",
                            "path": "/reference/input/rotation",
                            "subitems": []
                        },
                        {
                            "name": "running time",
                            "path": "/reference/input/running-time",
                            "subitems": []
                        },
                        {
                            "name": "set accelerometer range",
                            "path": "/reference/input/set-accelerometer-range",
                            "subitems": []
                        }
                    ]
                },
                {
                    "name": "Music",
                    "path": "/reference/music",
                    "subitems": [
                        {
                            "name": "play tone",
                            "path": "/reference/music/play-tone",
                            "subitems": []
                        },
                        {
                            "name": "ring tone",
                            "path": "/reference/music/ring-tone",
                            "subitems": []
                        },
                        {
                            "name": "rest",
                            "path": "/reference/music/rest",
                            "subitems": []
                        },
                        {
                            "name": "beat",
                            "path": "/reference/music/beat",
                            "subitems": []
                        },
                        {
                            "name": "tempo",
                            "path": "/reference/music/tempo",
                            "subitems": []
                        },
                        {
                            "name": "change tempo by",
                            "path": "/reference/music/change-tempo-by",
                            "subitems": []
                        },
                        {
                            "name": "set tempo",
                            "path": "/reference/music/set-tempo",
                            "subitems": []
                        }
                    ]
                },
                {
                    "name": "Led",
                    "path": "/reference/Neopixel",
                    "subitems": [
                        {
                            "name": "set brightness",
                            "path": "/reference/led/set-brightness",
                            "subitems": []
                        },
                        {
                            "name": "set color",
                            "path": "/reference/led/stop-animation",
                            "subitems": []
                        }
                    ]
                },
                {
                    "name": "Radio",
                    "path": "/reference/radio",
                    "subitems": [
                        {
                            "name": "send number",
                            "path": "/reference/radio/send-number",
                            "subitems": []
                        },
                        {
                            "name": "send value",
                            "path": "/reference/radio/send-value",
                            "subitems": []
                        },
                        {
                            "name": "send string",
                            "path": "/reference/radio/send-string",
                            "subitems": []
                        },
                        {
                            "name": "on received number",
                            "path": "/reference/radio/on-received-number",
                            "subitems": []
                        },
                        {
                            "name": "on received string",
                            "path": "/reference/radio/on-received-string",
                            "subitems": []
                        },
                        {
                            "name": "on received buffer",
                            "path": "/reference/radio/on-received-buffer",
                            "subitems": []
                        },
                        {
                            "name": "received packet",
                            "path": "/reference/radio/received-packet",
                            "subitems": []
                        },
                        {
                            "name": "set group",
                            "path": "/reference/radio/set-group",
                            "subitems": []
                        },
                        {
                            "name": "set transmit power",
                            "path": "/reference/radio/set-transmit-power",
                            "subitems": []
                        },
                        {
                            "name": "set transmit serial number",
                            "path": "/reference/radio/set-transmit-serial-number",
                            "subitems": []
                        },
                        {
                            "name": "on data packet received",
                            "path": "/reference/radio/on-data-packet-received",
                            "subitems": []
                        },
                        {
                            "name": "write received packet to serial",
                            "path": "/reference/radio/write-received-packet-to-serial",
                            "subitems": []
                        }
                    ]
                },
                {
                    "name": "Game",
                    "path": "/reference/game",
                    "subitems": [
                        {
                            "name": "create sprite",
                            "path": "/reference/game/create-sprite",
                            "subitems": []
                        },
                        {
                            "name": "delete",
                            "path": "/reference/game/delete",
                            "subitems": []
                        },
                        {
                            "name": "move",
                            "path": "/reference/game/move",
                            "subitems": []
                        },
                        {
                            "name": "turn",
                            "path": "/reference/game/turn",
                            "subitems": []
                        },
                        {
                            "name": "if on edge bounce",
                            "path": "/reference/game/if-on-edge-bounce",
                            "subitems": []
                        },
                        {
                            "name": "get",
                            "path": "/reference/game/get",
                            "subitems": []
                        },
                        {
                            "name": "set",
                            "path": "/reference/game/set",
                            "subitems": []
                        },
                        {
                            "name": "change",
                            "path": "/reference/game/change",
                            "subitems": []
                        },
                        {
                            "name": "is touching",
                            "path": "/reference/game/is-touching",
                            "subitems": []
                        },
                        {
                            "name": "is touching edge",
                            "path": "/reference/game/is-touching-edge",
                            "subitems": []
                        },
                        {
                            "name": "add score",
                            "path": "/reference/game/add-score",
                            "subitems": []
                        },
                        {
                            "name": "score",
                            "path": "/reference/game/score",
                            "subitems": []
                        },
                        {
                            "name": "set score",
                            "path": "/reference/game/set-score",
                            "subitems": []
                        },
                        {
                            "name": "set life",
                            "path": "/reference/game/set-life",
                            "subitems": []
                        },
                        {
                            "name": "add life",
                            "path": "/reference/game/add-life",
                            "subitems": []
                        },
                        {
                            "name": "remove life",
                            "path": "/reference/game/remove-life",
                            "subitems": []
                        },
                        {
                            "name": "start countdown",
                            "path": "/reference/game/start-countdown",
                            "subitems": []
                        },
                        {
                            "name": "game over",
                            "path": "/reference/game/game-over",
                            "subitems": []
                        },
                        {
                            "name": "pause",
                            "path": "/reference/game/pause",
                            "subitems": []
                        },
                        {
                            "name": "resume",
                            "path": "/reference/game/resume",
                            "subitems": []
                        }
                    ]
                },
                {
                    "name": "Images",
                    "path": "/reference/images",
                    "subitems": [
                        {
                            "name": "create image",
                            "path": "/reference/images/create-image",
                            "subitems": []
                        },
                        {
                            "name": "create big image",
                            "path": "/reference/images/create-big-image",
                            "subitems": []
                        },
                        {
                            "name": "show image",
                            "path": "/reference/images/show-image",
                            "subitems": []
                        },
                        {
                            "name": "scroll image",
                            "path": "/reference/images/scroll-image",
                            "subitems": []
                        },
                        {
                            "name": "arrow image",
                            "path": "/reference/images/arrow-image",
                            "subitems": []
                        },
                        {
                            "name": "icon image",
                            "path": "/reference/images/icon-image",
                            "subitems": []
                        },
                        {
                            "name": "arrow number",
                            "path": "/reference/images/arrow-number",
                            "subitems": []
                        }
                    ]
                },
                {
                    "name": "Pins",
                    "path": "/reference/pins",
                    "subitems": [
                        {
                            "name": "digital read pin",
                            "path": "/reference/pins/digital-read-pin",
                            "subitems": []
                        },
                        {
                            "name": "digital write pin",
                            "path": "/reference/pins/digital-write-pin",
                            "subitems": []
                        },
                        {
                            "name": "analog read pin",
                            "path": "/reference/pins/analog-read-pin",
                            "subitems": []
                        },
                        {
                            "name": "analog write pin",
                            "path": "/reference/pins/analog-write-pin",
                            "subitems": []
                        },
                        {
                            "name": "analog set period",
                            "path": "/reference/pins/analog-set-period",
                            "subitems": []
                        },
                        {
                            "name": "map",
                            "path": "/reference/pins/map",
                            "subitems": []
                        },
                        {
                            "name": "on pulsed",
                            "path": "/reference/pins/on-pulsed",
                            "subitems": []
                        },
                        {
                            "name": "pulse duration",
                            "path": "/reference/pins/pulse-duration",
                            "subitems": []
                        },
                        {
                            "name": "pulse in",
                            "path": "/reference/pins/pulse-in",
                            "subitems": []
                        },
                        {
                            "name": "servo write pin",
                            "path": "/reference/pins/servo-write-pin",
                            "subitems": []
                        },
                        {
                            "name": "servo set pulse",
                            "path": "/reference/pins/servo-set-pulse",
                            "subitems": []
                        },
                        {
                            "name": "i2c read number",
                            "path": "/reference/pins/i2c-read-number",
                            "subitems": []
                        },
                        {
                            "name": "i2c write number",
                            "path": "/reference/pins/i2c-write-number",
                            "subitems": []
                        },
                        {
                            "name": "set pull",
                            "path": "/reference/pins/set-pull",
                            "subitems": []
                        },
                        {
                            "name": "analog pitch",
                            "path": "/reference/pins/analog-pitch",
                            "subitems": []
                        },
                        {
                            "name": "analog set pitch pin",
                            "path": "/reference/pins/analog-set-pitch-pin",
                            "subitems": []
                        },
                        {
                            "name": "spi write",
                            "path": "/reference/pins/spi-write",
                            "subitems": []
                        },
                        {
                            "name": "spi Pins",
                            "path": "/reference/pins/spi-pins",
                            "subitems": []
                        },
                        {
                            "name": "spi format",
                            "path": "/reference/pins/spi-format",
                            "subitems": []
                        },
                        {
                            "name": "spi frequency",
                            "path": "/reference/pins/spi-frequency",
                            "subitems": []
                        }
                    ]
                },
                {
                    "name": "Serial",
                    "path": "/reference/serial",
                    "subitems": [
                        {
                            "name": "write line",
                            "path": "/reference/serial/write-line",
                            "subitems": []
                        },
                        {
                            "name": "write number",
                            "path": "/reference/serial/write-number",
                            "subitems": []
                        },
                        {
                            "name": "write value",
                            "path": "/reference/serial/write-value",
                            "subitems": []
                        },
                        {
                            "name": "write string",
                            "path": "/reference/serial/write-string",
                            "subitems": []
                        },
                        {
                            "name": "read until",
                            "path": "/reference/serial/read-until",
                            "subitems": []
                        },
                        {
                            "name": "read line",
                            "path": "/reference/serial/read-line",
                            "subitems": []
                        },
                        {
                            "name": "read string",
                            "path": "/reference/serial/read-string",
                            "subitems": []
                        },
                        {
                            "name": "on data received",
                            "path": "/reference/serial/on-data-received",
                            "subitems": []
                        },
                        {
                            "name": "redirect",
                            "path": "/reference/serial/redirect",
                            "subitems": []
                        },
                        {
                            "name": "redirect to usb",
                            "path": "/reference/serial/redirect-to-usb",
                            "subitems": []
                        },
                        {
                            "name": "write buffer",
                            "path": "/reference/serial/write-buffer",
                            "subitems": []
                        },
                        {
                            "name": "read buffer",
                            "path": "/reference/serial/read-buffer",
                            "subitems": []
                        }
                    ]
                },
                {
                    "name": "Control",
                    "path": "/reference/control",
                    "subitems": [
                        {
                            "name": "in background",
                            "path": "/reference/control/in-background",
                            "subitems": []
                        },
                        {
                            "name": "reset",
                            "path": "/reference/control/reset",
                            "subitems": []
                        },
                        {
                            "name": "wait micros",
                            "path": "/reference/control/wait-micros",
                            "subitems": []
                        },
                        {
                            "name": "on event",
                            "path": "/reference/control/on-event",
                            "subitems": []
                        },
                        {
                            "name": "raise event",
                            "path": "/reference/control/raise-event",
                            "subitems": []
                        },
                        {
                            "name": "event timestamp",
                            "path": "/reference/control/event-timestamp",
                            "subitems": []
                        },
                        {
                            "name": "event value",
                            "path": "/reference/control/event-value",
                            "subitems": []
                        }
                    ]
                },
                {
                    "name": "Bluetooth",
                    "path": "/reference/bluetooth",
                    "subitems": [
                        {
                            "name": "About",
                            "path": "/reference/bluetooth/about-bluetooth",
                            "subitems": []
                        },
                        {
                            "name": "Pairing",
                            "path": "/reference/bluetooth/bluetooth-pairing",
                            "subitems": []
                        },
                        {
                            "name": "on bluetooth connected",
                            "path": "/reference/bluetooth/on-bluetooth-connected",
                            "subitems": []
                        },
                        {
                            "name": "on bluetooth disconnected",
                            "path": "/reference/bluetooth/on-bluetooth-disconnected",
                            "subitems": []
                        },
                        {
                            "name": "start accelerometer service",
                            "path": "/reference/bluetooth/start-accelerometer-service",
                            "subitems": []
                        },
                        {
                            "name": "start button service",
                            "path": "/reference/bluetooth/start-button-service",
                            "subitems": []
                        },
                        {
                            "name": "start io pin service",
                            "path": "/reference/bluetooth/start-io-pin-service",
                            "subitems": []
                        },
                        {
                            "name": "start led service",
                            "path": "/reference/bluetooth/start-led-service",
                            "subitems": []
                        },
                        {
                            "name": "start magnetometer service",
                            "path": "/reference/bluetooth/start-magnetometer-service",
                            "subitems": []
                        },
                        {
                            "name": "start temperature service",
                            "path": "/reference/bluetooth/start-temperature-service",
                            "subitems": []
                        },
                        {
                            "name": "start uart service",
                            "path": "/reference/bluetooth/start-uart-service",
                            "subitems": []
                        },
                        {
                            "name": "uart read until",
                            "path": "/reference/bluetooth/uart-read-until",
                            "subitems": []
                        },
                        {
                            "name": "uart write string",
                            "path": "/reference/bluetooth/uart-write-string",
                            "subitems": []
                        },
                        {
                            "name": "uart write number",
                            "path": "/reference/bluetooth/uart-write-number",
                            "subitems": []
                        },
                        {
                            "name": "uart write value",
                            "path": "/reference/bluetooth/uart-write-value",
                            "subitems": []
                        },
                        {
                            "name": "advertise url",
                            "path": "/reference/bluetooth/advertise-url",
                            "subitems": []
                        },
                        {
                            "name": "stop advertising",
                            "path": "/reference/bluetooth/stop-advertising",
                            "subitems": []
                        },
                        {
                            "name": "advertise uid",
                            "path": "/reference/bluetooth/advertise-uid",
                            "subitems": []
                        },
                        {
                            "name": "advertise-uid-buffer",
                            "path": "/reference/bluetooth/advertise-uid-buffer",
                            "subitems": []
                        }
                    ]
                },
                {
                    "name": "Devices",
                    "path": "/reference/devices",
                    "subitems": [
                        {
                            "name": "tell camera to",
                            "path": "/reference/devices/tell-camera-to",
                            "subitems": []
                        },
                        {
                            "name": "tell remote control to",
                            "path": "/reference/devices/tell-remote-control-to",
                            "subitems": []
                        },
                        {
                            "name": "raise alert to",
                            "path": "/reference/devices/raise-alert-to",
                            "subitems": []
                        },
                        {
                            "name": "on notified",
                            "path": "/reference/devices/on-notified",
                            "subitems": []
                        },
                        {
                            "name": "on gamepad button",
                            "path": "/reference/devices/on-gamepad-button",
                            "subitems": []
                        },
                        {
                            "name": "signal strength",
                            "path": "/reference/devices/signal-strength",
                            "subitems": []
                        },
                        {
                            "name": "on signal strength changed",
                            "path": "/reference/devices/on-signal-strength-changed",
                            "subitems": []
                        }
                    ]
                }
            ]
        },
        {
            "name": "Program Blocks",
            "path": "/blocks",
            "subitems": [
                {
                    "name": "On Start",
                    "path": "/blocks/on-start",
                    "subitems": []
                },
                {
                    "name": "Loops",
                    "path": "/blocks/loops",
                    "subitems": [
                        {
                            "name": "repeat",
                            "path": "/blocks/loops/repeat",
                            "subitems": []
                        },
                        {
                            "name": "for",
                            "path": "/blocks/loops/for",
                            "subitems": []
                        },
                        {
                            "name": "while",
                            "path": "/blocks/loops/while",
                            "subitems": []
                        },
                        {
                            "name": "for of",
                            "path": "/blocks/loops/for-of",
                            "subitems": []
                        }
                    ]
                },
                {
                    "name": "Logic",
                    "path": "/blocks/logic",
                    "subitems": [
                        {
                            "name": "if",
                            "path": "/blocks/logic/if",
                            "subitems": []
                        },
                        {
                            "name": "Boolean",
                            "path": "/blocks/logic/boolean",
                            "subitems": []
                        }
                    ]
                },
                {
                    "name": "Variables",
                    "path": "/blocks/variables",
                    "subitems": [
                        {
                            "name": "assign",
                            "path": "/blocks/variables/assign",
                            "subitems": []
                        },
                        {
                            "name": "change var",
                            "path": "/blocks/variables/change",
                            "subitems": []
                        },
                        {
                            "name": "var",
                            "path": "/blocks/variables/var",
                            "subitems": []
                        }
                    ]
                },
                {
                    "name": "Math",
                    "path": "/blocks/math",
                    "subitems": []
                },
                {
                    "name": "JavaScript blocks",
                    "path": "/blocks/javascript-blocks",
                    "subitems": []
                },
                {
                    "name": "Custom blocks",
                    "path": "/blocks/custom",
                    "subitems": []
                }
            ]
        },
        {
            "name": "Python",
            "path": "/python",
            "subitems": [
                {
                    "name": "Calling",
                    "path": "/python/call",
                    "subitems": []
                },
                {
                    "name": "Sequencing",
                    "path": "/python/sequence",
                    "subitems": []
                },
                {
                    "name": "Variables",
                    "path": "/python/variables",
                    "subitems": []
                },
                {
                    "name": "Operators",
                    "path": "/python/operators",
                    "subitems": []
                },
                {
                    "name": "Statements",
                    "path": "/python/statements",
                    "subitems": []
                },
                {
                    "name": "Functions",
                    "path": "/python/functions",
                    "subitems": []
                },
                {
                    "name": "Classes",
                    "path": "/python/classes",
                    "subitems": []
                }
            ]
        },
        {
            "name": "JavaScript",
            "path": "/javascript",
            "subitems": [
                {
                    "name": "Calling",
                    "path": "/javascript/call",
                    "subitems": []
                },
                {
                    "name": "Sequencing",
                    "path": "/javascript/sequence",
                    "subitems": []
                },
                {
                    "name": "Variables",
                    "path": "/javascript/variables",
                    "subitems": []
                },
                {
                    "name": "Operators",
                    "path": "/javascript/operators",
                    "subitems": []
                },
                {
                    "name": "Statements",
                    "path": "/javascript/statements",
                    "subitems": []
                },
                {
                    "name": "Functions",
                    "path": "/javascript/functions",
                    "subitems": []
                },
                {
                    "name": "Types",
                    "path": "/javascript/types",
                    "subitems": []
                },
                {
                    "name": "Classes",
                    "path": "/javascript/classes",
                    "subitems": []
                },
                {
                    "name": "Interfaces",
                    "path": "/javascript/interfaces",
                    "subitems": []
                },
                {
                    "name": "Generics",
                    "path": "/javascript/generics",
                    "subitems": []
                }
            ]
        },
        {
            "name": "Types",
            "path": "/types",
            "subitems": [
                {
                    "name": "Number",
                    "path": "/types/number",
                    "subitems": []
                },
                {
                    "name": "String",
                    "path": "/types/string",
                    "subitems": []
                },
                {
                    "name": "Boolean",
                    "path": "/types/boolean",
                    "subitems": []
                },
                {
                    "name": "Array",
                    "path": "/types/array",
                    "subitems": []
                },
                {
                    "name": "Function",
                    "path": "/types/function",
                    "subitems": []
                }
            ]
        },
        {
            "name": "FAQ",
            "path": "/faq",
            "subitems": []
        },
        {
            "name": "Support",
            "path": "/support",
            "subitems": []
        }
    ],
    "id": "teknikio-bluebird",
    "title": "Teknikio Bluebird - Blocks / Javascript Editor",
    "name": "bluebird",
    "description": "A Blocks / Javascript code editor for the Teknikio Bluebird",
    "htmlDocIncludes": {}
}